Metadata-Version: 2.1
Name: zytestpip
Version: 1.0.3
Summary: This is the SDK for example.
Home-page: http://example.com
Author: bwz0328
Author-email: bwz0328@126.com
License: UNKNOWN
Platform: UNKNOWN
